LICENSE
README.rst
setup.cfg
setup.py
docs/changelog.rst
src/senaite/__init__.py
src/senaite.microorganism.egg-info/PKG-INFO
src/senaite.microorganism.egg-info/SOURCES.txt
src/senaite.microorganism.egg-info/dependency_links.txt
src/senaite.microorganism.egg-info/entry_points.txt
src/senaite.microorganism.egg-info/namespace_packages.txt
src/senaite.microorganism.egg-info/not-zip-safe
src/senaite.microorganism.egg-info/requires.txt
src/senaite.microorganism.egg-info/top_level.txt
src/senaite/microorganism/__init__.py
src/senaite/microorganism/config.py
src/senaite/microorganism/configure.zcml
src/senaite/microorganism/interfaces.py
src/senaite/microorganism/setuphandlers.py
src/senaite/microorganism/vocabularies.py
src/senaite/microorganism/browser/__init__.py
src/senaite/microorganism/browser/configure.zcml
src/senaite/microorganism/browser/content/__init__.py
src/senaite/microorganism/browser/content/configure.zcml
src/senaite/microorganism/browser/content/microorganismcategories.py
src/senaite/microorganism/browser/content/microorganismfolder.py
src/senaite/microorganism/browser/static/assets/icons/microorganism.svg
src/senaite/microorganism/browser/static/assets/icons/microorganism_categories.svg
src/senaite/microorganism/browser/static/assets/icons/microorganism_category.svg
src/senaite/microorganism/browser/static/assets/icons/microorganisms.svg
src/senaite/microorganism/browser/theme/__init__.py
src/senaite/microorganism/browser/theme/configure.zcml
src/senaite/microorganism/browser/theme/icons.py
src/senaite/microorganism/content/__init__.py
src/senaite/microorganism/content/microorganism.py
src/senaite/microorganism/content/microorganismcategories.py
src/senaite/microorganism/content/microorganismcategory.py
src/senaite/microorganism/content/microorganismfolder.py
src/senaite/microorganism/locales/senaite.microorganism.pot
src/senaite/microorganism/locales/cs/LC_MESSAGES/senaite.microorganism.po
src/senaite/microorganism/locales/de/LC_MESSAGES/senaite.microorganism.po
src/senaite/microorganism/locales/en/LC_MESSAGES/senaite.microorganism.po
src/senaite/microorganism/locales/es/LC_MESSAGES/senaite.microorganism.po
src/senaite/microorganism/profiles/default/browserlayer.xml
src/senaite/microorganism/profiles/default/metadata.xml
src/senaite/microorganism/profiles/default/senaite.microorganism.txt
src/senaite/microorganism/profiles/default/types.xml
